qnd/__init__.py
qnd/config.py
qnd/config_test.py
qnd/estimator.py
qnd/estimator_test.py
qnd/evaluate.py
qnd/evaluate_test.py
qnd/experiment.py
qnd/experiment_test.py
qnd/flag.py
qnd/flag_test.py
qnd/infer.py
qnd/infer_test.py
qnd/inputs.py
qnd/inputs_test.py
qnd/serve.py
qnd/test.py
qnd/test_test.py
qnd/train_and_evaluate.py
qnd/train_and_evaluate_test.py
qnd/util.py
qnd/util_test.py
tensorflow_qnd-0.1.11.dist-info/DESCRIPTION.rst
tensorflow_qnd-0.1.11.dist-info/METADATA
tensorflow_qnd-0.1.11.dist-info/RECORD
tensorflow_qnd-0.1.11.dist-info/WHEEL
tensorflow_qnd-0.1.11.dist-info/metadata.json
tensorflow_qnd-0.1.11.dist-info/top_level.txt
