Metadata-Version: 2.0
Name: tensorflow-qnd
Version: 0.1.11
Summary: Quick and Dirty TensorFlow command framework
Home-page: https://github.com/raviqqe/tensorflow-qnd/
Author: Yota Toyama
Author-email: raviqqe@gmail.com
License: Public Domain
Platform: UNKNOWN
Classifier: Development Status :: 3 - Alpha
Classifier: Intended Audience :: Developers
Classifier: License :: Public Domain
Classifier: Programming Language :: Python :: 3.5
Classifier: Programming Language :: Python :: 3.6
Classifier: Topic :: Scientific/Engineering :: Artificial Intelligence
Classifier: Topic :: System :: Networking
Requires-Dist: gargparse
